<?xml version="1.0" encoding="UTF-8" standalone="yes"?>
<items>



<item>
<title>[B][COLOR green]Além da Margem 2ª Temporada - 4k - 2024[/COLOR] [COLOR yellow] Dublada & Legendada [/COLOR][/B]</title>
<link>plugin://plugin.video.elementum/play?uri=magnet:?xt=urn:btih:336da8309e627b5cfe0c3f2f0fcec042bfed1935&dn=Outer.Range.S02.COMPLETE.1080p.AMZN.WEB.H264-SuccessfulCrab[TGx]&tr=udp%3A%2F%2Fopen.stealth.si%3A80%2Fannounce&tr=udp%3A%2F%2Fexodus.desync.com%3A6969%2Fannounce&tr=udp%3A%2F%2Ftracker.cyberia.is%3A6969%2Fannounce&tr=udp%3A%2F%2Ftracker.opentrackr.org%3A1337%2Fannounce&tr=udp%3A%2F%2Ftracker.torrent.eu.org%3A451%2Fannounce&tr=udp%3A%2F%2Fexplodie.org%3A6969%2Fannounce&tr=udp%3A%2F%2Ftracker.birkenwald.de%3A6969%2Fannounce&tr=udp%3A%2F%2Ftracker.moeking.me%3A6969%2Fannounce&tr=udp%3A%2F%2Fipv4.tracker.harry.lu%3A80%2Fannounce&tr=udp%3A%2F%2Ftracker.tiny-vps.com%3A6969%2Fannounce</link>
<thumbnail>https://www.themoviedb.org/t/p/w600_and_h900_bestv2/9leGmIDamsWJELYz0pZkr2EXUFf.jpg</thumbnail>
<genre>Faroeste, Mistério, Drama</genre>
<fanart>https://www.themoviedb.org/t/p/w600_and_h900_bestv2/9leGmIDamsWJELYz0pZkr2EXUFf.jpg</fanart>
<info>Um rancheiro a lutar pela sua terra e família encontra um mistério imperscrutável na orla da natureza selvagem do Wyoming.</info>
</item>

<item>
<title>[B][COLOR green]X-Men ’97 1ª Temporada - 1ª Temporada 4k - 2024[/COLOR] [COLOR yellow] Dublada & Legendada [/COLOR][/B]</title>
<link>plugin://plugin.video.elementum/play?uri=magnet:?xt=urn:btih:32a8b642a3034c8f14bf83d678804b4bf2c6b886&dn=X-Men.97.S01E03.HDR.2160p.WEB.H265-TheCuteness[TGx]&tr=udp%3A%2F%2Fopen.stealth.si%3A80%2Fannounce&tr=udp%3A%2F%2Fexodus.desync.com%3A6969%2Fannounce&tr=udp%3A%2F%2Ftracker.cyberia.is%3A6969%2Fannounce&tr=udp%3A%2F%2Ftracker.opentrackr.org%3A1337%2Fannounce&tr=udp%3A%2F%2Ftracker.torrent.eu.org%3A451%2Fannounce&tr=udp%3A%2F%2Fexplodie.org%3A6969%2Fannounce&tr=udp%3A%2F%2Ftracker.birkenwald.de%3A6969%2Fannounce&tr=udp%3A%2F%2Ftracker.moeking.me%3A6969%2Fannounce&tr=udp%3A%2F%2Fipv4.tracker.harry.lu%3A80%2Fannounce&tr=udp%3A%2F%2Ftracker.tiny-vps.com%3A6969%2Fannounce$nome=[B]Temporada 1 - Episódio 1[/B]</link>
<link>plugin://plugin.video.elementum/play?uri=magnet:?xt=urn:btih:32a8b642a3034c8f14bf83d678804b4bf2c6b886&dn=X-Men.97.S01E03.HDR.2160p.WEB.H265-TheCuteness[TGx]&tr=udp%3A%2F%2Fopen.stealth.si%3A80%2Fannounce&tr=udp%3A%2F%2Fexodus.desync.com%3A6969%2Fannounce&tr=udp%3A%2F%2Ftracker.cyberia.is%3A6969%2Fannounce&tr=udp%3A%2F%2Ftracker.opentrackr.org%3A1337%2Fannounce&tr=udp%3A%2F%2Ftracker.torrent.eu.org%3A451%2Fannounce&tr=udp%3A%2F%2Fexplodie.org%3A6969%2Fannounce&tr=udp%3A%2F%2Ftracker.birkenwald.de%3A6969%2Fannounce&tr=udp%3A%2F%2Ftracker.moeking.me%3A6969%2Fannounce&tr=udp%3A%2F%2Fipv4.tracker.harry.lu%3A80%2Fannounce&tr=udp%3A%2F%2Ftracker.tiny-vps.com%3A6969%2Fannounce$nome=[B]Temporada 1 - Episódio 2[/B]</link>
<link>plugin://plugin.video.elementum/play?uri=magnet:?xt=urn:btih:32a8b642a3034c8f14bf83d678804b4bf2c6b886&dn=X-Men.97.S01E03.HDR.2160p.WEB.H265-TheCuteness[TGx]&tr=udp%3A%2F%2Fopen.stealth.si%3A80%2Fannounce&tr=udp%3A%2F%2Fexodus.desync.com%3A6969%2Fannounce&tr=udp%3A%2F%2Ftracker.cyberia.is%3A6969%2Fannounce&tr=udp%3A%2F%2Ftracker.opentrackr.org%3A1337%2Fannounce&tr=udp%3A%2F%2Ftracker.torrent.eu.org%3A451%2Fannounce&tr=udp%3A%2F%2Fexplodie.org%3A6969%2Fannounce&tr=udp%3A%2F%2Ftracker.birkenwald.de%3A6969%2Fannounce&tr=udp%3A%2F%2Ftracker.moeking.me%3A6969%2Fannounce&tr=udp%3A%2F%2Fipv4.tracker.harry.lu%3A80%2Fannounce&tr=udp%3A%2F%2Ftracker.tiny-vps.com%3A6969%2Fannounce$nome=[B]Temporada 1 - Episódio 3[/B]</link>
<link>plugin://plugin.video.elementum/play?uri=magnet:?xt=urn:btih:6abdeb1663d57da7de924d611fa3c91ed27212d2&dn=X-Men.97.S01E04.1080p.WEB.H264-TheCuteness[TGx]&tr=udp%3A%2F%2Fopen.stealth.si%3A80%2Fannounce&tr=udp%3A%2F%2Fexodus.desync.com%3A6969%2Fannounce&tr=udp%3A%2F%2Ftracker.cyberia.is%3A6969%2Fannounce&tr=udp%3A%2F%2Ftracker.opentrackr.org%3A1337%2Fannounce&tr=udp%3A%2F%2Ftracker.torrent.eu.org%3A451%2Fannounce&tr=udp%3A%2F%2Fexplodie.org%3A6969%2Fannounce&tr=udp%3A%2F%2Ftracker.birkenwald.de%3A6969%2Fannounce&tr=udp%3A%2F%2Ftracker.moeking.me%3A6969%2Fannounce&tr=udp%3A%2F%2Fipv4.tracker.harry.lu%3A80%2Fannounce&tr=udp%3A%2F%2Ftracker.tiny-vps.com%3A6969%2Fannounce$nome=[B]Temporada 1 - Episódio 4[/B]</link>
<link>plugin://plugin.video.elementum/play?uri=magnet:?xt=urn:btih:1402baa419dff6b45bd579afccd8e7e469528db2&dn=X-Men.97.S01E05.HDR.2160p.WEB.H265-RVKD[TGx]&tr=udp%3A%2F%2Fopen.stealth.si%3A80%2Fannounce&tr=udp%3A%2F%2Fexodus.desync.com%3A6969%2Fannounce&tr=udp%3A%2F%2Ftracker.cyberia.is%3A6969%2Fannounce&tr=udp%3A%2F%2Ftracker.opentrackr.org%3A1337%2Fannounce&tr=udp%3A%2F%2Ftracker.torrent.eu.org%3A451%2Fannounce&tr=udp%3A%2F%2Fexplodie.org%3A6969%2Fannounce&tr=udp%3A%2F%2Ftracker.birkenwald.de%3A6969%2Fannounce&tr=udp%3A%2F%2Ftracker.moeking.me%3A6969%2Fannounce&tr=udp%3A%2F%2Fipv4.tracker.harry.lu%3A80%2Fannounce&tr=udp%3A%2F%2Ftracker.tiny-vps.com%3A6969%2Fannounce$nome=[B]Temporada 1 - Episódio 5[/B]</link>
<link>plugin://plugin.video.elementum/play?uri=magnet:?xt=urn:btih:8acfc3dc632672b47b609c7144b7d6d2558524aa&dn=X-Men.97.S01E06.HDR.2160p.WEB.h265-EDITH[TGx]&tr=udp%3A%2F%2Fopen.stealth.si%3A80%2Fannounce&tr=udp%3A%2F%2Fexodus.desync.com%3A6969%2Fannounce&tr=udp%3A%2F%2Ftracker.cyberia.is%3A6969%2Fannounce&tr=udp%3A%2F%2Ftracker.opentrackr.org%3A1337%2Fannounce&tr=udp%3A%2F%2Ftracker.torrent.eu.org%3A451%2Fannounce&tr=udp%3A%2F%2Fexplodie.org%3A6969%2Fannounce&tr=udp%3A%2F%2Ftracker.birkenwald.de%3A6969%2Fannounce&tr=udp%3A%2F%2Ftracker.moeking.me%3A6969%2Fannounce&tr=udp%3A%2F%2Fipv4.tracker.harry.lu%3A80%2Fannounce&tr=udp%3A%2F%2Ftracker.tiny-vps.com%3A6969%2Fannounce$nome=[B]Temporada 1 - Episódio 6[/B]</link>
<link>plugin://plugin.video.elementum/play?uri=magnet:?xt=urn:btih:c37ce5ffb0f3438f691e3f9c5a8fd8db63bc35aa&dn=X-Men.97.S01E07.HDR.2160p.WEB.H265-TheCuteness[TGx]&tr=udp%3A%2F%2Fopen.stealth.si%3A80%2Fannounce&tr=udp%3A%2F%2Fexodus.desync.com%3A6969%2Fannounce&tr=udp%3A%2F%2Ftracker.cyberia.is%3A6969%2Fannounce&tr=udp%3A%2F%2Ftracker.opentrackr.org%3A1337%2Fannounce&tr=udp%3A%2F%2Ftracker.torrent.eu.org%3A451%2Fannounce&tr=udp%3A%2F%2Fexplodie.org%3A6969%2Fannounce&tr=udp%3A%2F%2Ftracker.birkenwald.de%3A6969%2Fannounce&tr=udp%3A%2F%2Ftracker.moeking.me%3A6969%2Fannounce&tr=udp%3A%2F%2Fipv4.tracker.harry.lu%3A80%2Fannounce&tr=udp%3A%2F%2Ftracker.tiny-vps.com%3A6969%2Fannounce$nome=[B]Temporada 1 - Episódio 7[/B]</link>
<link>plugin://plugin.video.elementum/play?uri=magnet:?xt=urn:btih:9934bf7a7768637b74f52b0a04b3a118e987ed03&dn=X-Men.97.S01E08.HDR.2160p.WEB.h265-EDITH[TGx]&tr=udp%3A%2F%2Fopen.stealth.si%3A80%2Fannounce&tr=udp%3A%2F%2Fexodus.desync.com%3A6969%2Fannounce&tr=udp%3A%2F%2Ftracker.cyberia.is%3A6969%2Fannounce&tr=udp%3A%2F%2Ftracker.opentrackr.org%3A1337%2Fannounce&tr=udp%3A%2F%2Ftracker.torrent.eu.org%3A451%2Fannounce&tr=udp%3A%2F%2Fexplodie.org%3A6969%2Fannounce&tr=udp%3A%2F%2Ftracker.birkenwald.de%3A6969%2Fannounce&tr=udp%3A%2F%2Ftracker.moeking.me%3A6969%2Fannounce&tr=udp%3A%2F%2Fipv4.tracker.harry.lu%3A80%2Fannounce&tr=udp%3A%2F%2Ftracker.tiny-vps.com%3A6969%2Fannounce$nome=[B]Temporada 1 - Episódio 8[/B]</link>
<link>plugin://plugin.video.elementum/play?uri=magnet:?xt=urn:btih:64ff3c44c33e6ec5d8de7716ad157a22d38b7d2f&dn=X-Men.97.S01E09.HDR.2160p.WEB.H265-TheCuteness[TGx]&tr=udp%3A%2F%2Fopen.stealth.si%3A80%2Fannounce&tr=udp%3A%2F%2Fexodus.desync.com%3A6969%2Fannounce&tr=udp%3A%2F%2Ftracker.cyberia.is%3A6969%2Fannounce&tr=udp%3A%2F%2Ftracker.opentrackr.org%3A1337%2Fannounce&tr=udp%3A%2F%2Ftracker.torrent.eu.org%3A451%2Fannounce&tr=udp%3A%2F%2Fexplodie.org%3A6969%2Fannounce&tr=udp%3A%2F%2Ftracker.birkenwald.de%3A6969%2Fannounce&tr=udp%3A%2F%2Ftracker.moeking.me%3A6969%2Fannounce&tr=udp%3A%2F%2Fipv4.tracker.harry.lu%3A80%2Fannounce&tr=udp%3A%2F%2Ftracker.tiny-vps.com%3A6969%2Fannounce$nome=[B]Temporada 1 - Episódio 9[/B]</link>
<link>plugin://plugin.video.elementum/play?uri=magnet:?xt=urn:btih:64ff3c44c33e6ec5d8de7716ad157a22d38b7d2f&dn=X-Men.97.S01E09.HDR.2160p.WEB.H265-TheCuteness[TGx]&tr=udp%3A%2F%2Fopen.stealth.si%3A80%2Fannounce&tr=udp%3A%2F%2Fexodus.desync.com%3A6969%2Fannounce&tr=udp%3A%2F%2Ftracker.cyberia.is%3A6969%2Fannounce&tr=udp%3A%2F%2Ftracker.opentrackr.org%3A1337%2Fannounce&tr=udp%3A%2F%2Ftracker.torrent.eu.org%3A451%2Fannounce&tr=udp%3A%2F%2Fexplodie.org%3A6969%2Fannounce&tr=udp%3A%2F%2Ftracker.birkenwald.de%3A6969%2Fannounce&tr=udp%3A%2F%2Ftracker.moeking.me%3A6969%2Fannounce&tr=udp%3A%2F%2Fipv4.tracker.harry.lu%3A80%2Fannounce&tr=udp%3A%2F%2Ftracker.tiny-vps.com%3A6969%2Fannounce$nome=[B]Temporada 1 - Episódio 10[/B]</link>
<thumbnail>https://www.themoviedb.org/t/p/w600_and_h900_bestv2/3wWIbA1VPsWC0FHB3V1gUgsgEHG.jpg</thumbnail>
<genre>Animação, Action, Adventure, Sci-Fi, Fantasy</genre>
<fanart>https://www.themoviedb.org/t/p/w600_and_h900_bestv2/3wWIbA1VPsWC0FHB3V1gUgsgEHG.jpg</fanart>
<info>Continuando de onde ‘X-Men’ parou, os X-Men estão em um período de transição, lutando com a perda do Professor X. E enquanto seu mundo está em um estado tenso de calma quando se trata de relações mutantes-humanos— todo mundo sabe que isso provavelmente é temporário.</info>
</item>

V<item>
<title>[B][COLOR green]Mike - Além de Tyson - 1ª Temporada (2022)[/COLOR] [COLOR yellow] Dublada & Legendada [/COLOR][/B]</title>
<link>plugin://plugin.video.elementum/play?uri=magnet:?xt=urn:btih:d5845712c0d623b6080061eb8baf5c47c914a431&dn=VACATORRENT.COM..MKV.-LEGENDADO-..Mike.2022.S01.2160p.HULU.WEB-DL.x265.10bit.SDR.DDP5.1-NTb%5Brartv%5D&tr=http%3A%2F%2Ftracker.trackerfix.com%3A80%2Fannounce&tr=udp%3A%2F%2F9.rarbg.me%3A2730&tr=udp%3A%2F%2F9.rarbg.to%3A2990&tr=udp%3A%2F%2Ftracker.thinelephant.org%3A12760&tr=udp%3A%2F%2Ftracker.slowcheetah.org%3A14750</link>
<thumbnail>https://www.themoviedb.org/t/p/w600_and_h900_bestv2/2cZCfifyh5ElYv0rbFFqkqs0bp5.jpg</thumbnail>
<genre>Drama</genre>
<fanart>https://www.themoviedb.org/t/p/w600_and_h900_bestv2/2cZCfifyh5ElYv0rbFFqkqs0bp5.jpg</fanart>
<info>Explore a vida selvagem, trágica e controversa e a carreira do campeão peso-pesado Mike Tyson - uma das figuras mais polêmicas da cultura esportiva.</info>
</item>



</items>

